{
  "type": "quiz",
  "title": "Programming Paradigms",
  "assignment": "What is the programming paradigm that uses objects and classes called?",
  "maxScore": 8,
  "answer": {
    "type": "input",
    "correctAnswer": "object-oriented programming",
    "caseSensitive": false,
    "diacriticSensitive": false,
    "correctFeedback": "Exactly! OOP (object-oriented programming) organizes code around objects.",
    "incorrectFeedback": "We're looking for a paradigm where classes and inheritance are used."
  }
}
